autodistill_gpt_text/__init__.py
autodistill_gpt_text/model.py
autodistill_gpt_text-0.1.0.dist-info/METADATA
autodistill_gpt_text-0.1.0.dist-info/WHEEL
autodistill_gpt_text-0.1.0.dist-info/top_level.txt
autodistill_gpt_text-0.1.0.dist-info/RECORD
