Metadata-Version: 2.1
Name: autodistill-gpt-text
Version: 0.1.0
Summary: Model for use with Autodistill
Home-page: https://github.com/autodistill/autodistil-gpt-text
Author: capjamesg
Author-email: support@roboflow.com
Classifier: Programming Language :: Python :: 3
Classifier: License :: OSI Approved :: MIT License
Classifier: Operating System :: OS Independent
Requires-Python: >=3.7
Requires-Dist: autodistill
Requires-Dist: openai
Requires-Dist: tqdm
Requires-Dist: torch
Provides-Extra: dev
Requires-Dist: flake8 ; extra == 'dev'
Requires-Dist: black ==22.3.0 ; extra == 'dev'
Requires-Dist: isort ; extra == 'dev'
Requires-Dist: twine ; extra == 'dev'
Requires-Dist: pytest ; extra == 'dev'
Requires-Dist: wheel ; extra == 'dev'
